[
  {
    "timestamp": "2024-05-28T09:43:49.776278",
    "altitude": 381,
    "pressure": 190,
    "temperature": 25
  },
  {
    "timestamp": "2024-05-28T09:43:50.788884",
    "altitude": 765,
    "pressure": 6,
    "temperature": 31
  },
  {
    "timestamp": "2024-05-28T09:43:51.800157",
    "altitude": 551,
    "pressure": 449,
    "temperature": 13
  },
  {
    "timestamp": "2024-05-28T09:43:52.815068",
    "altitude": 781,
    "pressure": 286,
    "temperature": 4
  },
  {
    "timestamp": "2024-05-28T09:43:53.838250",
    "altitude": 910,
    "pressure": 168,
    "temperature": 5
  },
  {
    "timestamp": "2024-05-28T09:43:54.978202",
    "altitude": 89,
    "pressure": 153,
    "temperature": 38
  },
  {
    "timestamp": "2024-05-28T09:43:59.453742",
    "altitude": 809,
    "pressure": 235,
    "temperature": 18
  },
  {
    "timestamp": "2024-05-28T09:44:00.482764",
    "altitude": 433,
    "pressure": 304,
    "temperature": 24
  },
  {
    "timestamp": "2024-05-28T09:44:01.493406",
    "altitude": 175,
    "pressure": 249,
    "temperature": 5
  },
  {
    "timestamp": "2024-05-28T09:44:02.515689",
    "altitude": 580,
    "pressure": 76,
    "temperature": 24
  },
  {
    "timestamp": "2024-05-28T09:44:03.528350",
    "altitude": 639,
    "pressure": 376,
    "temperature": 39
  },
  {
    "timestamp": "2024-05-28T09:44:04.539595",
    "altitude": 793,
    "pressure": 8,
    "temperature": 6
  },
  {
    "timestamp": "2024-05-28T09:44:05.558097",
    "altitude": 633,
    "pressure": 295,
    "temperature": 35
  },
  {
    "timestamp": "2024-05-28T09:44:06.592154",
    "altitude": 399,
    "pressure": 380,
    "temperature": 21
  },
  {
    "timestamp": "2024-05-28T09:44:07.621044",
    "altitude": 922,
    "pressure": 456,
    "temperature": 22
  },
  {
    "timestamp": "2024-05-28T09:44:08.822882",
    "altitude": 769,
    "pressure": 299,
    "temperature": 5
  },
  {
    "timestamp": "2024-05-28T09:44:09.869071",
    "altitude": 125,
    "pressure": 235,
    "temperature": 8
  },
  {
    "timestamp": "2024-05-28T09:44:10.883337",
    "altitude": 115,
    "pressure": 109,
    "temperature": 39
  },
  {
    "timestamp": "2024-05-28T09:44:11.892989",
    "altitude": 256,
    "pressure": 134,
    "temperature": 13
  },
  {
    "timestamp": "2024-05-28T09:44:12.914784",
    "altitude": 829,
    "pressure": 127,
    "temperature": 16
  },
  {
    "timestamp": "2024-05-28T09:44:13.925374",
    "altitude": 678,
    "pressure": 432,
    "temperature": 21
  },
  {
    "timestamp": "2024-05-28T09:44:14.944569",
    "altitude": 309,
    "pressure": 163,
    "temperature": 8
  },
  {
    "timestamp": "2024-05-28T09:44:15.957367",
    "altitude": 251,
    "pressure": 364,
    "temperature": 11
  },
  {
    "timestamp": "2024-05-28T09:44:16.972494",
    "altitude": 341,
    "pressure": 392,
    "temperature": 2
  },
  {
    "timestamp": "2024-05-28T09:44:17.996091",
    "altitude": 714,
    "pressure": 150,
    "temperature": 29
  },
  {
    "timestamp": "2024-05-28T09:44:19.058885",
    "altitude": 909,
    "pressure": 64,
    "temperature": 17
  },
  {
    "timestamp": "2024-05-28T09:44:20.164143",
    "altitude": 1,
    "pressure": 301,
    "temperature": 18
  },
  {
    "timestamp": "2024-05-28T09:44:21.190382",
    "altitude": 124,
    "pressure": 396,
    "temperature": 30
  },
  {
    "timestamp": "2024-05-28T09:44:22.286244",
    "altitude": 615,
    "pressure": 115,
    "temperature": 34
  },
  {
    "timestamp": "2024-05-28T09:44:23.380448",
    "altitude": 684,
    "pressure": 216,
    "temperature": 33
  },
  {
    "timestamp": "2024-05-28T09:44:24.489460",
    "altitude": 279,
    "pressure": 456,
    "temperature": 13
  },
  {
    "timestamp": "2024-05-28T09:44:25.509910",
    "altitude": 185,
    "pressure": 11,
    "temperature": 31
  },
  {
    "timestamp": "2024-05-28T09:44:26.522217",
    "altitude": 241,
    "pressure": 101,
    "temperature": 39
  },
  {
    "timestamp": "2024-05-28T09:44:27.535415",
    "altitude": 960,
    "pressure": 225,
    "temperature": 35
  },
  {
    "timestamp": "2024-05-28T09:44:28.572177",
    "altitude": 655,
    "pressure": 336,
    "temperature": 30
  },
  {
    "timestamp": "2024-05-28T09:44:29.586692",
    "altitude": 346,
    "pressure": 149,
    "temperature": 12
  },
  {
    "timestamp": "2024-05-28T09:44:30.868180",
    "altitude": 492,
    "pressure": 332,
    "temperature": 12
  },
  {
    "timestamp": "2024-05-28T09:44:31.933050",
    "altitude": 618,
    "pressure": 341,
    "temperature": 0
  },
  {
    "timestamp": "2024-05-28T09:44:32.961048",
    "altitude": 375,
    "pressure": 314,
    "temperature": 32
  },
  {
    "timestamp": "2024-05-28T09:44:34.069056",
    "altitude": 246,
    "pressure": 292,
    "temperature": 26
  },
  {
    "timestamp": "2024-05-28T09:44:35.087048",
    "altitude": 754,
    "pressure": 67,
    "temperature": 25
  },
  {
    "timestamp": "2024-05-28T09:44:36.103242",
    "altitude": 316,
    "pressure": 313,
    "temperature": 32
  },
  {
    "timestamp": "2024-05-28T09:44:37.120226",
    "altitude": 972,
    "pressure": 444,
    "temperature": 28
  },
  {
    "timestamp": "2024-05-28T09:44:38.136466",
    "altitude": 309,
    "pressure": 464,
    "temperature": 18
  },
  {
    "timestamp": "2024-05-28T09:44:39.154528",
    "altitude": 621,
    "pressure": 121,
    "temperature": 0
  },
  {
    "timestamp": "2024-05-28T09:44:40.180360",
    "altitude": 873,
    "pressure": 80,
    "temperature": 37
  },
  {
    "timestamp": "2024-05-28T09:44:41.206748",
    "altitude": 586,
    "pressure": 443,
    "temperature": 15
  },
  {
    "timestamp": "2024-05-28T09:44:42.228845",
    "altitude": 459,
    "pressure": 294,
    "temperature": 33
  },
  {
    "timestamp": "2024-05-28T09:44:43.254162",
    "altitude": 719,
    "pressure": 297,
    "temperature": 30
  },
  {
    "timestamp": "2024-05-28T09:44:44.271684",
    "altitude": 879,
    "pressure": 77,
    "temperature": 27
  },
  {
    "timestamp": "2024-05-28T09:44:45.292194",
    "altitude": 205,
    "pressure": 291,
    "temperature": 24
  },
  {
    "timestamp": "2024-05-28T09:44:46.307260",
    "altitude": 802,
    "pressure": 177,
    "temperature": 15
  },
  {
    "timestamp": "2024-05-28T09:44:47.321510",
    "altitude": 37,
    "pressure": 492,
    "temperature": 35
  },
  {
    "timestamp": "2024-05-28T09:44:48.336676",
    "altitude": 848,
    "pressure": 414,
    "temperature": 21
  },
  {
    "timestamp": "2024-05-28T09:44:49.360809",
    "altitude": 742,
    "pressure": 462,
    "temperature": 39
  },
  {
    "timestamp": "2024-05-28T09:44:50.371889",
    "altitude": 137,
    "pressure": 50,
    "temperature": 15
  },
  {
    "timestamp": "2024-05-28T09:44:51.393986",
    "altitude": 956,
    "pressure": 57,
    "temperature": 38
  },
  {
    "timestamp": "2024-05-28T09:44:52.413924",
    "altitude": 974,
    "pressure": 320,
    "temperature": 18
  },
  {
    "timestamp": "2024-05-28T09:44:53.438385",
    "altitude": 139,
    "pressure": 341,
    "temperature": 14
  },
  {
    "timestamp": "2024-05-28T09:44:54.458221",
    "altitude": 209,
    "pressure": 280,
    "temperature": 38
  },
  {
    "timestamp": "2024-05-28T09:44:55.482525",
    "altitude": 501,
    "pressure": 387,
    "temperature": 22
  },
  {
    "timestamp": "2024-05-28T09:44:56.520675",
    "altitude": 687,
    "pressure": 317,
    "temperature": 37
  },
  {
    "timestamp": "2024-05-28T09:44:57.535302",
    "altitude": 237,
    "pressure": 484,
    "temperature": 4
  },
  {
    "timestamp": "2024-05-28T09:44:58.553852",
    "altitude": 91,
    "pressure": 322,
    "temperature": 14
  },
  {
    "timestamp": "2024-05-28T09:44:59.571906",
    "altitude": 637,
    "pressure": 68,
    "temperature": 21
  },
  {
    "timestamp": "2024-05-28T09:45:00.583432",
    "altitude": 234,
    "pressure": 470,
    "temperature": 36
  },
  {
    "timestamp": "2024-05-28T09:45:01.596573",
    "altitude": 156,
    "pressure": 495,
    "temperature": 24
  },
  {
    "timestamp": "2024-05-28T09:45:02.616733",
    "altitude": 698,
    "pressure": 339,
    "temperature": 34
  },
  {
    "timestamp": "2024-05-28T09:45:03.632169",
    "altitude": 820,
    "pressure": 256,
    "temperature": 19
  },
  {
    "timestamp": "2024-05-28T09:45:04.657028",
    "altitude": 191,
    "pressure": 153,
    "temperature": 34
  },
  {
    "timestamp": "2024-05-28T09:45:05.670851",
    "altitude": 736,
    "pressure": 407,
    "temperature": 28
  },
  {
    "timestamp": "2024-05-28T09:45:06.686812",
    "altitude": 968,
    "pressure": 257,
    "temperature": 0
  },
  {
    "timestamp": "2024-05-28T09:45:07.708939",
    "altitude": 379,
    "pressure": 79,
    "temperature": 28
  },
  {
    "timestamp": "2024-05-28T09:45:08.729955",
    "altitude": 695,
    "pressure": 473,
    "temperature": 35
  },
  {
    "timestamp": "2024-05-28T09:45:09.751979",
    "altitude": 693,
    "pressure": 406,
    "temperature": 18
  },
  {
    "timestamp": "2024-05-28T09:45:10.778175",
    "altitude": 353,
    "pressure": 252,
    "temperature": 15
  },
  {
    "timestamp": "2024-05-28T09:45:11.790566",
    "altitude": 144,
    "pressure": 484,
    "temperature": 22
  },
  {
    "timestamp": "2024-05-28T09:45:12.813608",
    "altitude": 487,
    "pressure": 9,
    "temperature": 2
  },
  {
    "timestamp": "2024-05-28T09:45:13.829839",
    "altitude": 101,
    "pressure": 32,
    "temperature": 12
  },
  {
    "timestamp": "2024-05-28T09:45:14.847042",
    "altitude": 796,
    "pressure": 28,
    "temperature": 6
  },
  {
    "timestamp": "2024-05-28T09:45:15.873053",
    "altitude": 51,
    "pressure": 315,
    "temperature": 39
  },
  {
    "timestamp": "2024-05-28T09:45:17.163298",
    "altitude": 22,
    "pressure": 386,
    "temperature": 7
  },
  {
    "timestamp": "2024-05-28T09:45:18.324102",
    "altitude": 128,
    "pressure": 87,
    "temperature": 25
  },
  {
    "timestamp": "2024-05-28T09:45:19.346140",
    "altitude": 10,
    "pressure": 28,
    "temperature": 33
  },
  {
    "timestamp": "2024-05-28T09:45:20.361488",
    "altitude": 576,
    "pressure": 482,
    "temperature": 4
  },
  {
    "timestamp": "2024-05-28T09:45:21.379631",
    "altitude": 107,
    "pressure": 331,
    "temperature": 13
  },
  {
    "timestamp": "2024-05-28T09:45:22.393682",
    "altitude": 421,
    "pressure": 204,
    "temperature": 35
  },
  {
    "timestamp": "2024-05-28T09:45:23.411695",
    "altitude": 422,
    "pressure": 169,
    "temperature": 16
  },
  {
    "timestamp": "2024-05-28T09:45:24.430664",
    "altitude": 791,
    "pressure": 68,
    "temperature": 27
  },
  {
    "timestamp": "2024-05-28T09:45:25.451716",
    "altitude": 64,
    "pressure": 376,
    "temperature": 5
  },
  {
    "timestamp": "2024-05-28T09:45:26.476205",
    "altitude": 152,
    "pressure": 96,
    "temperature": 29
  },
  {
    "timestamp": "2024-05-28T09:45:27.495363",
    "altitude": 888,
    "pressure": 379,
    "temperature": 31
  },
  {
    "timestamp": "2024-05-28T09:45:28.506399",
    "altitude": 142,
    "pressure": 488,
    "temperature": 25
  },
  {
    "timestamp": "2024-05-28T09:45:29.527525",
    "altitude": 384,
    "pressure": 458,
    "temperature": 25
  },
  {
    "timestamp": "2024-05-28T09:45:30.547390",
    "altitude": 707,
    "pressure": 474,
    "temperature": 0
  },
  {
    "timestamp": "2024-05-28T09:45:31.594089",
    "altitude": 399,
    "pressure": 173,
    "temperature": 22
  },
  {
    "timestamp": "2024-05-28T09:45:32.612546",
    "altitude": 793,
    "pressure": 401,
    "temperature": 21
  },
  {
    "timestamp": "2024-05-28T09:45:33.624834",
    "altitude": 13,
    "pressure": 316,
    "temperature": 10
  },
  {
    "timestamp": "2024-05-28T09:45:34.676981",
    "altitude": 928,
    "pressure": 61,
    "temperature": 7
  },
  {
    "timestamp": "2024-05-28T09:45:35.774002",
    "altitude": 180,
    "pressure": 301,
    "temperature": 9
  },
  {
    "timestamp": "2024-05-28T09:45:36.789968",
    "altitude": 444,
    "pressure": 269,
    "temperature": 16
  },
  {
    "timestamp": "2024-05-28T09:45:37.809970",
    "altitude": 490,
    "pressure": 160,
    "temperature": 24
  },
  {
    "timestamp": "2024-05-28T09:45:38.836982",
    "altitude": 731,
    "pressure": 236,
    "temperature": 27
  },
  {
    "timestamp": "2024-05-28T09:45:39.872498",
    "altitude": 554,
    "pressure": 11,
    "temperature": 17
  },
  {
    "timestamp": "2024-05-28T09:45:40.901214",
    "altitude": 756,
    "pressure": 227,
    "temperature": 6
  },
  {
    "timestamp": "2024-05-28T09:45:41.933704",
    "altitude": 543,
    "pressure": 41,
    "temperature": 3
  },
  {
    "timestamp": "2024-05-28T09:45:42.960698",
    "altitude": 173,
    "pressure": 266,
    "temperature": 39
  },
  {
    "timestamp": "2024-05-28T09:45:43.984781",
    "altitude": 900,
    "pressure": 130,
    "temperature": 11
  },
  {
    "timestamp": "2024-05-28T09:45:45.013352",
    "altitude": 283,
    "pressure": 389,
    "temperature": 30
  },
  {
    "timestamp": "2024-05-28T09:45:46.034356",
    "altitude": 143,
    "pressure": 3,
    "temperature": 6
  },
  {
    "timestamp": "2024-05-28T09:45:47.057355",
    "altitude": 386,
    "pressure": 275,
    "temperature": 22
  },
  {
    "timestamp": "2024-05-28T09:45:48.081575",
    "altitude": 415,
    "pressure": 202,
    "temperature": 20
  },
  {
    "timestamp": "2024-05-28T09:45:49.102476",
    "altitude": 248,
    "pressure": 456,
    "temperature": 36
  },
  {
    "timestamp": "2024-05-28T09:45:50.129479",
    "altitude": 821,
    "pressure": 121,
    "temperature": 38
  },
  {
    "timestamp": "2024-05-28T09:45:51.152134",
    "altitude": 191,
    "pressure": 340,
    "temperature": 1
  },
  {
    "timestamp": "2024-05-28T09:45:52.175936",
    "altitude": 569,
    "pressure": 257,
    "temperature": 9
  },
  {
    "timestamp": "2024-05-28T09:45:53.189131",
    "altitude": 422,
    "pressure": 337,
    "temperature": 27
  },
  {
    "timestamp": "2024-05-28T09:45:54.208003",
    "altitude": 204,
    "pressure": 175,
    "temperature": 2
  },
  {
    "timestamp": "2024-05-28T09:45:55.238132",
    "altitude": 719,
    "pressure": 365,
    "temperature": 3
  },
  {
    "timestamp": "2024-05-28T09:45:56.251627",
    "altitude": 7,
    "pressure": 295,
    "temperature": 10
  },
  {
    "timestamp": "2024-05-28T09:45:57.273627",
    "altitude": 456,
    "pressure": 373,
    "temperature": 12
  },
  {
    "timestamp": "2024-05-28T09:45:58.302374",
    "altitude": 566,
    "pressure": 293,
    "temperature": 30
  },
  {
    "timestamp": "2024-05-28T09:45:59.328217",
    "altitude": 732,
    "pressure": 231,
    "temperature": 31
  },
  {
    "timestamp": "2024-05-28T09:46:00.359991",
    "altitude": 162,
    "pressure": 475,
    "temperature": 25
  },
  {
    "timestamp": "2024-05-28T09:46:01.377994",
    "altitude": 922,
    "pressure": 220,
    "temperature": 30
  },
  {
    "timestamp": "2024-05-28T09:46:02.404981",
    "altitude": 473,
    "pressure": 232,
    "temperature": 8
  },
  {
    "timestamp": "2024-05-28T09:46:03.452140",
    "altitude": 853,
    "pressure": 466,
    "temperature": 38
  },
  {
    "timestamp": "2024-05-28T09:46:04.476301",
    "altitude": 400,
    "pressure": 215,
    "temperature": 18
  },
  {
    "timestamp": "2024-05-28T09:46:05.507399",
    "altitude": 736,
    "pressure": 250,
    "temperature": 34
  },
  {
    "timestamp": "2024-05-28T09:46:06.552510",
    "altitude": 518,
    "pressure": 383,
    "temperature": 30
  },
  {
    "timestamp": "2024-05-28T09:46:07.578532",
    "altitude": 243,
    "pressure": 266,
    "temperature": 8
  },
  {
    "timestamp": "2024-05-28T09:46:08.596625",
    "altitude": 238,
    "pressure": 141,
    "temperature": 10
  },
  {
    "timestamp": "2024-05-28T09:46:09.629618",
    "altitude": 23,
    "pressure": 43,
    "temperature": 1
  },
  {
    "timestamp": "2024-05-28T09:46:10.663627",
    "altitude": 606,
    "pressure": 57,
    "temperature": 10
  },
  {
    "timestamp": "2024-05-28T09:46:11.687824",
    "altitude": 589,
    "pressure": 144,
    "temperature": 9
  },
  {
    "timestamp": "2024-05-28T09:46:12.712585",
    "altitude": 561,
    "pressure": 275,
    "temperature": 38
  },
  {
    "timestamp": "2024-05-28T09:46:13.745359",
    "altitude": 314,
    "pressure": 449,
    "temperature": 28
  },
  {
    "timestamp": "2024-05-28T09:46:14.766002",
    "altitude": 984,
    "pressure": 188,
    "temperature": 0
  },
  {
    "timestamp": "2024-05-28T09:46:15.791393",
    "altitude": 960,
    "pressure": 113,
    "temperature": 0
  },
  {
    "timestamp": "2024-05-28T09:46:16.817902",
    "altitude": 111,
    "pressure": 328,
    "temperature": 35
  },
  {
    "timestamp": "2024-05-28T09:46:17.849500",
    "altitude": 346,
    "pressure": 315,
    "temperature": 24
  },
  {
    "timestamp": "2024-05-28T09:46:18.901497",
    "altitude": 208,
    "pressure": 462,
    "temperature": 16
  },
  {
    "timestamp": "2024-05-28T09:46:20.064017",
    "altitude": 4,
    "pressure": 105,
    "temperature": 4
  },
  {
    "timestamp": "2024-05-28T09:46:21.123020",
    "altitude": 167,
    "pressure": 277,
    "temperature": 17
  },
  {
    "timestamp": "2024-05-28T09:46:22.188583",
    "altitude": 609,
    "pressure": 412,
    "temperature": 23
  },
  {
    "timestamp": "2024-05-28T09:46:23.284425",
    "altitude": 611,
    "pressure": 212,
    "temperature": 2
  },
  {
    "timestamp": "2024-05-28T09:46:24.455422",
    "altitude": 565,
    "pressure": 189,
    "temperature": 2
  },
  {
    "timestamp": "2024-05-28T09:46:25.515889",
    "altitude": 598,
    "pressure": 114,
    "temperature": 16
  },
  {
    "timestamp": "2024-05-28T09:46:26.553304",
    "altitude": 695,
    "pressure": 283,
    "temperature": 5
  },
  {
    "timestamp": "2024-05-28T09:46:27.588380",
    "altitude": 175,
    "pressure": 112,
    "temperature": 2
  },
  {
    "timestamp": "2024-05-28T09:46:28.649456",
    "altitude": 653,
    "pressure": 220,
    "temperature": 34
  },
  {
    "timestamp": "2024-05-28T09:46:29.666563",
    "altitude": 954,
    "pressure": 277,
    "temperature": 21
  },
  {
    "timestamp": "2024-05-28T09:46:30.692558",
    "altitude": 881,
    "pressure": 336,
    "temperature": 20
  },
  {
    "timestamp": "2024-05-28T09:46:31.738559",
    "altitude": 281,
    "pressure": 193,
    "temperature": 36
  },
  {
    "timestamp": "2024-05-28T09:46:32.852498",
    "altitude": 735,
    "pressure": 196,
    "temperature": 28
  },
  {
    "timestamp": "2024-05-28T09:46:33.885499",
    "altitude": 26,
    "pressure": 225,
    "temperature": 21
  },
  {
    "timestamp": "2024-05-28T09:46:34.913499",
    "altitude": 380,
    "pressure": 475,
    "temperature": 17
  },
  {
    "timestamp": "2024-05-28T09:46:35.957629",
    "altitude": 914,
    "pressure": 441,
    "temperature": 8
  },
  {
    "timestamp": "2024-05-28T09:46:36.988390",
    "altitude": 879,
    "pressure": 451,
    "temperature": 25
  },
  {
    "timestamp": "2024-05-28T09:46:38.009095",
    "altitude": 403,
    "pressure": 175,
    "temperature": 34
  },
  {
    "timestamp": "2024-05-28T09:46:39.046099",
    "altitude": 751,
    "pressure": 71,
    "temperature": 34
  },
  {
    "timestamp": "2024-05-28T09:46:40.091098",
    "altitude": 445,
    "pressure": 317,
    "temperature": 39
  },
  {
    "timestamp": "2024-05-28T09:46:41.125144",
    "altitude": 792,
    "pressure": 300,
    "temperature": 25
  },
  {
    "timestamp": "2024-05-28T09:46:42.207952",
    "altitude": 829,
    "pressure": 363,
    "temperature": 39
  },
  {
    "timestamp": "2024-05-28T09:46:43.322393",
    "altitude": 139,
    "pressure": 479,
    "temperature": 27
  },
  {
    "timestamp": "2024-05-28T09:46:44.395510",
    "altitude": 71,
    "pressure": 455,
    "temperature": 35
  },
  {
    "timestamp": "2024-05-28T09:46:45.414872",
    "altitude": 866,
    "pressure": 377,
    "temperature": 17
  },
  {
    "timestamp": "2024-05-28T09:46:46.433838",
    "altitude": 562,
    "pressure": 263,
    "temperature": 23
  },
  {
    "timestamp": "2024-05-28T09:46:47.473243",
    "altitude": 663,
    "pressure": 166,
    "temperature": 4
  },
  {
    "timestamp": "2024-05-28T09:46:48.500783",
    "altitude": 835,
    "pressure": 261,
    "temperature": 36
  },
  {
    "timestamp": "2024-05-28T09:46:49.570323",
    "altitude": 410,
    "pressure": 229,
    "temperature": 39
  },
  {
    "timestamp": "2024-05-28T09:46:50.629326",
    "altitude": 708,
    "pressure": 195,
    "temperature": 10
  },
  {
    "timestamp": "2024-05-28T09:46:51.652321",
    "altitude": 60,
    "pressure": 7,
    "temperature": 26
  },
  {
    "timestamp": "2024-05-28T09:46:52.689439",
    "altitude": 533,
    "pressure": 278,
    "temperature": 5
  },
  {
    "timestamp": "2024-05-28T09:46:53.706959",
    "altitude": 222,
    "pressure": 366,
    "temperature": 18
  },
  {
    "timestamp": "2024-05-28T09:46:54.734654",
    "altitude": 519,
    "pressure": 239,
    "temperature": 18
  },
  {
    "timestamp": "2024-05-28T09:46:55.953698",
    "altitude": 750,
    "pressure": 277,
    "temperature": 31
  },
  {
    "timestamp": "2024-05-28T09:46:57.195066",
    "altitude": 311,
    "pressure": 442,
    "temperature": 24
  },
  {
    "timestamp": "2024-05-28T09:46:58.224573",
    "altitude": 301,
    "pressure": 442,
    "temperature": 6
  },
  {
    "timestamp": "2024-05-28T09:46:59.244511",
    "altitude": 297,
    "pressure": 133,
    "temperature": 2
  },
  {
    "timestamp": "2024-05-28T09:47:00.265490",
    "altitude": 92,
    "pressure": 429,
    "temperature": 4
  },
  {
    "timestamp": "2024-05-28T09:47:01.278707",
    "altitude": 449,
    "pressure": 97,
    "temperature": 37
  },
  {
    "timestamp": "2024-05-28T09:47:02.297241",
    "altitude": 326,
    "pressure": 470,
    "temperature": 13
  },
  {
    "timestamp": "2024-05-28T09:47:03.320320",
    "altitude": 474,
    "pressure": 443,
    "temperature": 8
  },
  {
    "timestamp": "2024-05-28T09:47:04.341672",
    "altitude": 962,
    "pressure": 93,
    "temperature": 4
  },
  {
    "timestamp": "2024-05-28T09:47:05.361148",
    "altitude": 20,
    "pressure": 400,
    "temperature": 5
  },
  {
    "timestamp": "2024-05-28T09:47:06.383649",
    "altitude": 622,
    "pressure": 367,
    "temperature": 23
  },
  {
    "timestamp": "2024-05-28T09:47:07.398616",
    "altitude": 843,
    "pressure": 310,
    "temperature": 7
  },
  {
    "timestamp": "2024-05-28T09:47:08.421562",
    "altitude": 804,
    "pressure": 361,
    "temperature": 13
  },
  {
    "timestamp": "2024-05-28T09:47:09.445356",
    "altitude": 670,
    "pressure": 185,
    "temperature": 13
  },
  {
    "timestamp": "2024-05-28T09:47:10.471770",
    "altitude": 511,
    "pressure": 478,
    "temperature": 39
  },
  {
    "timestamp": "2024-05-28T09:47:11.521380",
    "altitude": 878,
    "pressure": 476,
    "temperature": 13
  },
  {
    "timestamp": "2024-05-28T09:47:12.552405",
    "altitude": 553,
    "pressure": 376,
    "temperature": 34
  },
  {
    "timestamp": "2024-05-28T09:47:13.576460",
    "altitude": 754,
    "pressure": 38,
    "temperature": 39
  },
  {
    "timestamp": "2024-05-28T09:47:14.679770",
    "altitude": 793,
    "pressure": 61,
    "temperature": 38
  },
  {
    "timestamp": "2024-05-28T09:47:15.703572",
    "altitude": 663,
    "pressure": 448,
    "temperature": 26
  },
  {
    "timestamp": "2024-05-28T09:47:16.872763",
    "altitude": 479,
    "pressure": 366,
    "temperature": 18
  },
  {
    "timestamp": "2024-05-28T09:47:17.976406",
    "altitude": 929,
    "pressure": 62,
    "temperature": 29
  },
  {
    "timestamp": "2024-05-28T09:47:19.016441",
    "altitude": 919,
    "pressure": 198,
    "temperature": 1
  },
  {
    "timestamp": "2024-05-28T09:47:20.063161",
    "altitude": 147,
    "pressure": 385,
    "temperature": 30
  },
  {
    "timestamp": "2024-05-28T09:47:21.085936",
    "altitude": 57,
    "pressure": 312,
    "temperature": 2
  },
  {
    "timestamp": "2024-05-28T09:47:22.112370",
    "altitude": 15,
    "pressure": 371,
    "temperature": 13
  },
  {
    "timestamp": "2024-05-28T09:47:23.136211",
    "altitude": 199,
    "pressure": 132,
    "temperature": 19
  },
  {
    "timestamp": "2024-05-28T09:47:24.155287",
    "altitude": 27,
    "pressure": 64,
    "temperature": 14
  },
  {
    "timestamp": "2024-05-28T09:47:25.180103",
    "altitude": 87,
    "pressure": 158,
    "temperature": 39
  },
  {
    "timestamp": "2024-05-28T09:47:26.206407",
    "altitude": 462,
    "pressure": 142,
    "temperature": 9
  },
  {
    "timestamp": "2024-05-28T09:47:27.232094",
    "altitude": 392,
    "pressure": 27,
    "temperature": 9
  },
  {
    "timestamp": "2024-05-28T09:47:28.260832",
    "altitude": 817,
    "pressure": 171,
    "temperature": 34
  },
  {
    "timestamp": "2024-05-28T09:47:29.275523",
    "altitude": 1,
    "pressure": 427,
    "temperature": 29
  },
  {
    "timestamp": "2024-05-28T09:47:30.300546",
    "altitude": 888,
    "pressure": 352,
    "temperature": 23
  },
  {
    "timestamp": "2024-05-28T09:47:31.328929",
    "altitude": 790,
    "pressure": 420,
    "temperature": 11
  },
  {
    "timestamp": "2024-05-28T09:47:32.380713",
    "altitude": 241,
    "pressure": 251,
    "temperature": 3
  },
  {
    "timestamp": "2024-05-28T09:47:33.434715",
    "altitude": 786,
    "pressure": 121,
    "temperature": 15
  },
  {
    "timestamp": "2024-05-28T09:47:34.468705",
    "altitude": 249,
    "pressure": 414,
    "temperature": 5
  },
  {
    "timestamp": "2024-05-28T09:47:35.487038",
    "altitude": 101,
    "pressure": 118,
    "temperature": 26
  },
  {
    "timestamp": "2024-05-28T09:47:36.514508",
    "altitude": 550,
    "pressure": 402,
    "temperature": 18
  },
  {
    "timestamp": "2024-05-28T09:47:37.557807",
    "altitude": 6,
    "pressure": 391,
    "temperature": 8
  },
  {
    "timestamp": "2024-05-28T09:47:38.577753",
    "altitude": 968,
    "pressure": 197,
    "temperature": 37
  },
  {
    "timestamp": "2024-05-28T09:47:39.608319",
    "altitude": 181,
    "pressure": 259,
    "temperature": 39
  },
  {
    "timestamp": "2024-05-28T09:47:40.622043",
    "altitude": 657,
    "pressure": 377,
    "temperature": 5
  },
  {
    "timestamp": "2024-05-28T09:47:41.641343",
    "altitude": 850,
    "pressure": 218,
    "temperature": 24
  },
  {
    "timestamp": "2024-05-28T09:47:42.666355",
    "altitude": 653,
    "pressure": 303,
    "temperature": 21
  },
  {
    "timestamp": "2024-05-28T09:47:43.688561",
    "altitude": 865,
    "pressure": 192,
    "temperature": 26
  },
  {
    "timestamp": "2024-05-28T09:47:44.717559",
    "altitude": 582,
    "pressure": 369,
    "temperature": 34
  },
  {
    "timestamp": "2024-05-28T09:47:45.739904",
    "altitude": 355,
    "pressure": 433,
    "temperature": 29
  },
  {
    "timestamp": "2024-05-28T09:47:46.756789",
    "altitude": 263,
    "pressure": 259,
    "temperature": 3
  },
  {
    "timestamp": "2024-05-28T09:47:47.783007",
    "altitude": 817,
    "pressure": 183,
    "temperature": 26
  },
  {
    "timestamp": "2024-05-28T09:47:48.803045",
    "altitude": 760,
    "pressure": 217,
    "temperature": 17
  },
  {
    "timestamp": "2024-05-28T09:47:49.827043",
    "altitude": 479,
    "pressure": 41,
    "temperature": 6
  },
  {
    "timestamp": "2024-05-28T09:47:50.958520",
    "altitude": 490,
    "pressure": 60,
    "temperature": 9
  },
  {
    "timestamp": "2024-05-28T09:47:51.982818",
    "altitude": 519,
    "pressure": 271,
    "temperature": 22
  },
  {
    "timestamp": "2024-05-28T09:47:52.996107",
    "altitude": 465,
    "pressure": 176,
    "temperature": 13
  },
  {
    "timestamp": "2024-05-28T09:47:54.014590",
    "altitude": 536,
    "pressure": 452,
    "temperature": 32
  },
  {
    "timestamp": "2024-05-28T09:47:55.034573",
    "altitude": 438,
    "pressure": 121,
    "temperature": 29
  },
  {
    "timestamp": "2024-05-28T09:47:56.060329",
    "altitude": 34,
    "pressure": 52,
    "temperature": 3
  },
  {
    "timestamp": "2024-05-28T09:47:57.124297",
    "altitude": 594,
    "pressure": 154,
    "temperature": 32
  },
  {
    "timestamp": "2024-05-28T09:47:58.151314",
    "altitude": 200,
    "pressure": 118,
    "temperature": 8
  },
  {
    "timestamp": "2024-05-28T09:47:59.172372",
    "altitude": 957,
    "pressure": 172,
    "temperature": 19
  },
  {
    "timestamp": "2024-05-28T09:48:00.193599",
    "altitude": 5,
    "pressure": 331,
    "temperature": 32
  },
  {
    "timestamp": "2024-05-28T09:48:01.222320",
    "altitude": 707,
    "pressure": 416,
    "temperature": 0
  },
  {
    "timestamp": "2024-05-28T09:48:02.241335",
    "altitude": 732,
    "pressure": 60,
    "temperature": 12
  },
  {
    "timestamp": "2024-05-28T09:48:03.264772",
    "altitude": 969,
    "pressure": 202,
    "temperature": 6
  },
  {
    "timestamp": "2024-05-28T09:48:04.293259",
    "altitude": 911,
    "pressure": 102,
    "temperature": 2
  },
  {
    "timestamp": "2024-05-28T09:48:05.309495",
    "altitude": 979,
    "pressure": 175,
    "temperature": 17
  },
  {
    "timestamp": "2024-05-28T09:48:06.330351",
    "altitude": 748,
    "pressure": 221,
    "temperature": 34
  },
  {
    "timestamp": "2024-05-28T09:48:07.345361",
    "altitude": 260,
    "pressure": 397,
    "temperature": 31
  },
  {
    "timestamp": "2024-05-28T09:48:08.362406",
    "altitude": 66,
    "pressure": 173,
    "temperature": 36
  },
  {
    "timestamp": "2024-05-28T09:48:09.377193",
    "altitude": 941,
    "pressure": 85,
    "temperature": 0
  },
  {
    "timestamp": "2024-05-28T09:48:10.396744",
    "altitude": 63,
    "pressure": 392,
    "temperature": 34
  },
  {
    "timestamp": "2024-05-28T09:48:11.413780",
    "altitude": 76,
    "pressure": 312,
    "temperature": 36
  },
  {
    "timestamp": "2024-05-28T09:48:12.717563",
    "altitude": 175,
    "pressure": 60,
    "temperature": 8
  },
  {
    "timestamp": "2024-05-28T09:48:13.936565",
    "altitude": 778,
    "pressure": 164,
    "temperature": 38
  },
  {
    "timestamp": "2024-05-28T09:48:15.003563",
    "altitude": 85,
    "pressure": 160,
    "temperature": 1
  },
  {
    "timestamp": "2024-05-28T09:48:16.065373",
    "altitude": 853,
    "pressure": 258,
    "temperature": 5
  },
  {
    "timestamp": "2024-05-28T09:48:17.090202",
    "altitude": 832,
    "pressure": 82,
    "temperature": 0
  },
  {
    "timestamp": "2024-05-28T09:48:18.104890",
    "altitude": 376,
    "pressure": 459,
    "temperature": 0
  },
  {
    "timestamp": "2024-05-28T09:48:19.121946",
    "altitude": 253,
    "pressure": 108,
    "temperature": 21
  },
  {
    "timestamp": "2024-05-28T09:48:20.139078",
    "altitude": 487,
    "pressure": 262,
    "temperature": 4
  },
  {
    "timestamp": "2024-05-28T09:48:21.159829",
    "altitude": 243,
    "pressure": 273,
    "temperature": 0
  },
  {
    "timestamp": "2024-05-28T09:48:22.186356",
    "altitude": 204,
    "pressure": 426,
    "temperature": 3
  },
  {
    "timestamp": "2024-05-28T09:48:23.207236",
    "altitude": 490,
    "pressure": 417,
    "temperature": 5
  },
  {
    "timestamp": "2024-05-28T09:48:24.228708",
    "altitude": 426,
    "pressure": 369,
    "temperature": 26
  },
  {
    "timestamp": "2024-05-28T09:48:25.254686",
    "altitude": 564,
    "pressure": 0,
    "temperature": 29
  },
  {
    "timestamp": "2024-05-28T09:48:26.282183",
    "altitude": 980,
    "pressure": 439,
    "temperature": 18
  },
  {
    "timestamp": "2024-05-28T09:48:27.303888",
    "altitude": 887,
    "pressure": 108,
    "temperature": 24
  },
  {
    "timestamp": "2024-05-28T09:48:28.320056",
    "altitude": 517,
    "pressure": 497,
    "temperature": 2
  },
  {
    "timestamp": "2024-05-28T09:48:29.348161",
    "altitude": 587,
    "pressure": 415,
    "temperature": 9
  },
  {
    "timestamp": "2024-05-28T09:48:30.369247",
    "altitude": 161,
    "pressure": 47,
    "temperature": 34
  },
  {
    "timestamp": "2024-05-28T09:48:31.387886",
    "altitude": 705,
    "pressure": 488,
    "temperature": 38
  },
  {
    "timestamp": "2024-05-28T09:48:32.413890",
    "altitude": 447,
    "pressure": 0,
    "temperature": 33
  },
  {
    "timestamp": "2024-05-28T09:48:33.438219",
    "altitude": 877,
    "pressure": 488,
    "temperature": 13
  },
  {
    "timestamp": "2024-05-28T09:48:34.460287",
    "altitude": 611,
    "pressure": 298,
    "temperature": 39
  },
  {
    "timestamp": "2024-05-28T09:48:35.491224",
    "altitude": 860,
    "pressure": 212,
    "temperature": 0
  },
  {
    "timestamp": "2024-05-28T09:48:36.517336",
    "altitude": 685,
    "pressure": 350,
    "temperature": 5
  },
  {
    "timestamp": "2024-05-28T09:48:37.538383",
    "altitude": 326,
    "pressure": 79,
    "temperature": 25
  },
  {
    "timestamp": "2024-05-28T09:48:38.563177",
    "altitude": 883,
    "pressure": 184,
    "temperature": 20
  },
  {
    "timestamp": "2024-05-28T09:48:39.586185",
    "altitude": 605,
    "pressure": 69,
    "temperature": 36
  },
  {
    "timestamp": "2024-05-28T09:48:40.610173",
    "altitude": 913,
    "pressure": 435,
    "temperature": 37
  },
  {
    "timestamp": "2024-05-28T09:48:41.632228",
    "altitude": 41,
    "pressure": 231,
    "temperature": 6
  },
  {
    "timestamp": "2024-05-28T09:48:42.655312",
    "altitude": 882,
    "pressure": 224,
    "temperature": 22
  },
  {
    "timestamp": "2024-05-28T09:48:43.676080",
    "altitude": 475,
    "pressure": 254,
    "temperature": 34
  },
  {
    "timestamp": "2024-05-28T09:48:44.695471",
    "altitude": 669,
    "pressure": 351,
    "temperature": 30
  },
  {
    "timestamp": "2024-05-28T09:48:45.726269",
    "altitude": 568,
    "pressure": 336,
    "temperature": 7
  },
  {
    "timestamp": "2024-05-28T09:48:46.752057",
    "altitude": 23,
    "pressure": 201,
    "temperature": 39
  },
  {
    "timestamp": "2024-05-28T09:48:47.778006",
    "altitude": 575,
    "pressure": 104,
    "temperature": 9
  },
  {
    "timestamp": "2024-05-28T09:48:48.800105",
    "altitude": 126,
    "pressure": 122,
    "temperature": 36
  },
  {
    "timestamp": "2024-05-28T09:48:49.832219",
    "altitude": 350,
    "pressure": 322,
    "temperature": 31
  },
  {
    "timestamp": "2024-05-28T09:48:50.858313",
    "altitude": 625,
    "pressure": 355,
    "temperature": 7
  },
  {
    "timestamp": "2024-05-28T09:48:51.886536",
    "altitude": 585,
    "pressure": 100,
    "temperature": 3
  },
  {
    "timestamp": "2024-05-28T09:48:52.916921",
    "altitude": 412,
    "pressure": 390,
    "temperature": 36
  },
  {
    "timestamp": "2024-05-28T09:48:53.945093",
    "altitude": 908,
    "pressure": 16,
    "temperature": 3
  },
  {
    "timestamp": "2024-05-28T09:48:54.975281",
    "altitude": 254,
    "pressure": 116,
    "temperature": 32
  },
  {
    "timestamp": "2024-05-28T09:48:55.994972",
    "altitude": 155,
    "pressure": 235,
    "temperature": 30
  },
  {
    "timestamp": "2024-05-28T09:48:57.025295",
    "altitude": 692,
    "pressure": 455,
    "temperature": 9
  },
  {
    "timestamp": "2024-05-28T09:48:58.053029",
    "altitude": 166,
    "pressure": 96,
    "temperature": 6
  },
  {
    "timestamp": "2024-05-28T09:48:59.077209",
    "altitude": 587,
    "pressure": 307,
    "temperature": 22
  },
  {
    "timestamp": "2024-05-28T09:49:00.098675",
    "altitude": 515,
    "pressure": 56,
    "temperature": 35
  },
  {
    "timestamp": "2024-05-28T09:49:01.368196",
    "altitude": 436,
    "pressure": 243,
    "temperature": 26
  },
  {
    "timestamp": "2024-05-28T09:49:02.435901",
    "altitude": 952,
    "pressure": 439,
    "temperature": 21
  },
  {
    "timestamp": "2024-05-28T09:49:03.536866",
    "altitude": 101,
    "pressure": 0,
    "temperature": 11
  },
  {
    "timestamp": "2024-05-28T09:49:04.685291",
    "altitude": 732,
    "pressure": 8,
    "temperature": 19
  },
  {
    "timestamp": "2024-05-28T09:49:05.712258",
    "altitude": 651,
    "pressure": 290,
    "temperature": 11
  },
  {
    "timestamp": "2024-05-28T09:49:06.736879",
    "altitude": 521,
    "pressure": 347,
    "temperature": 8
  },
  {
    "timestamp": "2024-05-28T09:49:07.752307",
    "altitude": 647,
    "pressure": 261,
    "temperature": 32
  },
  {
    "timestamp": "2024-05-28T09:49:08.783600",
    "altitude": 13,
    "pressure": 157,
    "temperature": 2
  },
  {
    "timestamp": "2024-05-28T09:49:09.806090",
    "altitude": 380,
    "pressure": 307,
    "temperature": 3
  },
  {
    "timestamp": "2024-05-28T09:49:10.907786",
    "altitude": 467,
    "pressure": 272,
    "temperature": 36
  },
  {
    "timestamp": "2024-05-28T09:49:11.933083",
    "altitude": 782,
    "pressure": 153,
    "temperature": 5
  },
  {
    "timestamp": "2024-05-28T09:49:12.960441",
    "altitude": 908,
    "pressure": 423,
    "temperature": 6
  },
  {
    "timestamp": "2024-05-28T09:49:13.991537",
    "altitude": 771,
    "pressure": 379,
    "temperature": 19
  },
  {
    "timestamp": "2024-05-28T09:49:15.059500",
    "altitude": 657,
    "pressure": 252,
    "temperature": 6
  },
  {
    "timestamp": "2024-05-28T09:49:16.098235",
    "altitude": 10,
    "pressure": 380,
    "temperature": 24
  },
  {
    "timestamp": "2024-05-28T09:49:17.124364",
    "altitude": 617,
    "pressure": 448,
    "temperature": 39
  },
  {
    "timestamp": "2024-05-28T09:49:18.152917",
    "altitude": 381,
    "pressure": 24,
    "temperature": 26
  },
  {
    "timestamp": "2024-05-28T09:49:19.179848",
    "altitude": 400,
    "pressure": 491,
    "temperature": 1
  },
  {
    "timestamp": "2024-05-28T09:49:20.203136",
    "altitude": 322,
    "pressure": 240,
    "temperature": 12
  },
  {
    "timestamp": "2024-05-28T09:49:21.218389",
    "altitude": 717,
    "pressure": 20,
    "temperature": 4
  },
  {
    "timestamp": "2024-05-28T09:49:22.240862",
    "altitude": 833,
    "pressure": 282,
    "temperature": 6
  },
  {
    "timestamp": "2024-05-28T09:49:23.263977",
    "altitude": 892,
    "pressure": 201,
    "temperature": 6
  },
  {
    "timestamp": "2024-05-28T09:49:24.287744",
    "altitude": 562,
    "pressure": 357,
    "temperature": 14
  },
  {
    "timestamp": "2024-05-28T09:49:25.307208",
    "altitude": 944,
    "pressure": 363,
    "temperature": 23
  },
  {
    "timestamp": "2024-05-28T09:49:26.429977",
    "altitude": 951,
    "pressure": 207,
    "temperature": 1
  },
  {
    "timestamp": "2024-05-28T09:49:27.447311",
    "altitude": 301,
    "pressure": 385,
    "temperature": 12
  },
  {
    "timestamp": "2024-05-28T09:49:28.492867",
    "altitude": 60,
    "pressure": 410,
    "temperature": 11
  },
  {
    "timestamp": "2024-05-28T09:49:29.553874",
    "altitude": 84,
    "pressure": 16,
    "temperature": 39
  },
  {
    "timestamp": "2024-05-28T09:49:30.577111",
    "altitude": 798,
    "pressure": 191,
    "temperature": 25
  },
  {
    "timestamp": "2024-05-28T09:49:31.676199",
    "altitude": 496,
    "pressure": 222,
    "temperature": 23
  },
  {
    "timestamp": "2024-05-28T09:49:32.745006",
    "altitude": 744,
    "pressure": 367,
    "temperature": 20
  },
  {
    "timestamp": "2024-05-28T09:49:33.799008",
    "altitude": 709,
    "pressure": 419,
    "temperature": 0
  },
  {
    "timestamp": "2024-05-28T09:49:34.967983",
    "altitude": 860,
    "pressure": 46,
    "temperature": 19
  },
  {
    "timestamp": "2024-05-28T09:49:36.072980",
    "altitude": 35,
    "pressure": 325,
    "temperature": 8
  },
  {
    "timestamp": "2024-05-28T09:49:37.101344",
    "altitude": 295,
    "pressure": 115,
    "temperature": 5
  },
  {
    "timestamp": "2024-05-28T09:49:38.129387",
    "altitude": 707,
    "pressure": 207,
    "temperature": 5
  },
  {
    "timestamp": "2024-05-28T09:49:39.441728",
    "altitude": 536,
    "pressure": 263,
    "temperature": 29
  },
  {
    "timestamp": "2024-05-28T09:49:40.516965",
    "altitude": 224,
    "pressure": 261,
    "temperature": 37
  },
  {
    "timestamp": "2024-05-28T09:49:41.681951",
    "altitude": 689,
    "pressure": 148,
    "temperature": 25
  },
  {
    "timestamp": "2024-05-28T09:49:42.717151",
    "altitude": 130,
    "pressure": 8,
    "temperature": 21
  },
  {
    "timestamp": "2024-05-28T09:49:43.744281",
    "altitude": 807,
    "pressure": 429,
    "temperature": 4
  },
  {
    "timestamp": "2024-05-28T09:49:44.761255",
    "altitude": 286,
    "pressure": 237,
    "temperature": 12
  },
  {
    "timestamp": "2024-05-28T09:49:45.778167",
    "altitude": 664,
    "pressure": 478,
    "temperature": 19
  },
  {
    "timestamp": "2024-05-28T09:49:46.809364",
    "altitude": 663,
    "pressure": 333,
    "temperature": 20
  },
  {
    "timestamp": "2024-05-28T09:49:47.833945",
    "altitude": 251,
    "pressure": 175,
    "temperature": 20
  },
  {
    "timestamp": "2024-05-28T09:49:48.862016",
    "altitude": 298,
    "pressure": 63,
    "temperature": 25
  },
  {
    "timestamp": "2024-05-28T09:49:49.884908",
    "altitude": 428,
    "pressure": 173,
    "temperature": 4
  },
  {
    "timestamp": "2024-05-28T09:49:50.915076",
    "altitude": 907,
    "pressure": 86,
    "temperature": 36
  },
  {
    "timestamp": "2024-05-28T09:49:51.943519",
    "altitude": 277,
    "pressure": 170,
    "temperature": 37
  },
  {
    "timestamp": "2024-05-28T09:49:52.979321",
    "altitude": 541,
    "pressure": 233,
    "temperature": 25
  },
  {
    "timestamp": "2024-05-28T09:49:54.005323",
    "altitude": 250,
    "pressure": 243,
    "temperature": 22
  },
  {
    "timestamp": "2024-05-28T09:49:55.066353",
    "altitude": 579,
    "pressure": 465,
    "temperature": 13
  },
  {
    "timestamp": "2024-05-28T09:49:56.100797",
    "altitude": 210,
    "pressure": 411,
    "temperature": 35
  },
  {
    "timestamp": "2024-05-28T09:49:57.131482",
    "altitude": 202,
    "pressure": 225,
    "temperature": 31
  },
  {
    "timestamp": "2024-05-28T09:49:58.164035",
    "altitude": 186,
    "pressure": 397,
    "temperature": 17
  },
  {
    "timestamp": "2024-05-28T09:49:59.187630",
    "altitude": 689,
    "pressure": 147,
    "temperature": 33
  },
  {
    "timestamp": "2024-05-28T09:50:00.203839",
    "altitude": 134,
    "pressure": 270,
    "temperature": 3
  },
  {
    "timestamp": "2024-05-28T09:50:01.233308",
    "altitude": 796,
    "pressure": 317,
    "temperature": 27
  },
  {
    "timestamp": "2024-05-28T09:50:02.261718",
    "altitude": 595,
    "pressure": 9,
    "temperature": 24
  },
  {
    "timestamp": "2024-05-28T09:50:03.281567",
    "altitude": 594,
    "pressure": 190,
    "temperature": 27
  },
  {
    "timestamp": "2024-05-28T09:50:04.309496",
    "altitude": 189,
    "pressure": 338,
    "temperature": 26
  },
  {
    "timestamp": "2024-05-28T09:50:05.339896",
    "altitude": 801,
    "pressure": 110,
    "temperature": 15
  },
  {
    "timestamp": "2024-05-28T09:50:06.367035",
    "altitude": 502,
    "pressure": 308,
    "temperature": 3
  },
  {
    "timestamp": "2024-05-28T09:50:07.392049",
    "altitude": 823,
    "pressure": 112,
    "temperature": 23
  },
  {
    "timestamp": "2024-05-28T09:50:08.422302",
    "altitude": 856,
    "pressure": 410,
    "temperature": 20
  },
  {
    "timestamp": "2024-05-28T10:59:03.538923",
    "altitude": 456,
    "pressure": 345,
    "temperature": 22
  },
  {
    "timestamp": "2024-05-28T10:59:04.603249",
    "altitude": 323,
    "pressure": 352,
    "temperature": 9
  },
  {
    "timestamp": "2024-05-28T10:59:05.670341",
    "altitude": 352,
    "pressure": 289,
    "temperature": 29
  },
  {
    "timestamp": "2024-05-28T10:59:06.694468",
    "altitude": 143,
    "pressure": 79,
    "temperature": 12
  },
  {
    "timestamp": "2024-05-28T10:59:07.721787",
    "altitude": 54,
    "pressure": 336,
    "temperature": 16
  },
  {
    "timestamp": "2024-05-28T10:59:08.750271",
    "altitude": 436,
    "pressure": 381,
    "temperature": 32
  },
  {
    "timestamp": "2024-05-28T10:59:09.777280",
    "altitude": 779,
    "pressure": 396,
    "temperature": 3
  },
  {
    "timestamp": "2024-05-28T10:59:10.811712",
    "altitude": 117,
    "pressure": 84,
    "temperature": 7
  },
  {
    "timestamp": "2024-05-28T10:59:11.847035",
    "altitude": 598,
    "pressure": 376,
    "temperature": 32
  },
  {
    "timestamp": "2024-05-28T10:59:12.877777",
    "altitude": 989,
    "pressure": 87,
    "temperature": 5
  },
  {
    "timestamp": "2024-05-28T10:59:13.913275",
    "altitude": 247,
    "pressure": 226,
    "temperature": 2
  },
  {
    "timestamp": "2024-05-28T10:59:14.943168",
    "altitude": 136,
    "pressure": 245,
    "temperature": 10
  },
  {
    "timestamp": "2024-05-28T10:59:15.978157",
    "altitude": 597,
    "pressure": 310,
    "temperature": 23
  },
  {
    "timestamp": "2024-05-28T10:59:17.017434",
    "altitude": 274,
    "pressure": 89,
    "temperature": 7
  },
  {
    "timestamp": "2024-05-28T10:59:18.056883",
    "altitude": 909,
    "pressure": 306,
    "temperature": 5
  },
  {
    "timestamp": "2024-05-28T10:59:19.094927",
    "altitude": 960,
    "pressure": 89,
    "temperature": 39
  },
  {
    "timestamp": "2024-05-28T10:59:20.163784",
    "altitude": 258,
    "pressure": 415,
    "temperature": 6
  },
  {
    "timestamp": "2024-05-28T10:59:21.199741",
    "altitude": 283,
    "pressure": 17,
    "temperature": 18
  },
  {
    "timestamp": "2024-05-28T10:59:22.224907",
    "altitude": 50,
    "pressure": 273,
    "temperature": 11
  },
  {
    "timestamp": "2024-05-28T10:59:23.249916",
    "altitude": 39,
    "pressure": 211,
    "temperature": 24
  },
  {
    "timestamp": "2024-05-28T10:59:24.292720",
    "altitude": 247,
    "pressure": 240,
    "temperature": 4
  },
  {
    "timestamp": "2024-05-28T10:59:25.317815",
    "altitude": 898,
    "pressure": 379,
    "temperature": 3
  },
  {
    "timestamp": "2024-05-28T10:59:26.358840",
    "altitude": 522,
    "pressure": 264,
    "temperature": 15
  },
  {
    "timestamp": "2024-05-28T10:59:27.422201",
    "altitude": 464,
    "pressure": 296,
    "temperature": 27
  },
  {
    "timestamp": "2024-05-28T10:59:28.453072",
    "altitude": 786,
    "pressure": 75,
    "temperature": 12
  },
  {
    "timestamp": "2024-05-28T10:59:29.483826",
    "altitude": 571,
    "pressure": 475,
    "temperature": 8
  },
  {
    "timestamp": "2024-05-28T10:59:30.528862",
    "altitude": 518,
    "pressure": 470,
    "temperature": 38
  },
  {
    "timestamp": "2024-05-28T10:59:31.566622",
    "altitude": 105,
    "pressure": 32,
    "temperature": 13
  },
  {
    "timestamp": "2024-05-28T10:59:32.604686",
    "altitude": 254,
    "pressure": 325,
    "temperature": 5
  },
  {
    "timestamp": "2024-05-28T10:59:33.637806",
    "altitude": 997,
    "pressure": 79,
    "temperature": 15
  },
  {
    "timestamp": "2024-05-28T10:59:34.677332",
    "altitude": 857,
    "pressure": 190,
    "temperature": 26
  },
  {
    "timestamp": "2024-05-28T10:59:35.721588",
    "altitude": 468,
    "pressure": 428,
    "temperature": 6
  },
  {
    "timestamp": "2024-05-28T10:59:36.764336",
    "altitude": 787,
    "pressure": 314,
    "temperature": 10
  },
  {
    "timestamp": "2024-05-28T10:59:37.804541",
    "altitude": 211,
    "pressure": 420,
    "temperature": 35
  },
  {
    "timestamp": "2024-05-28T10:59:38.836717",
    "altitude": 674,
    "pressure": 477,
    "temperature": 9
  },
  {
    "timestamp": "2024-05-28T10:59:39.949486",
    "altitude": 276,
    "pressure": 34,
    "temperature": 16
  },
  {
    "timestamp": "2024-05-28T10:59:41.270640",
    "altitude": 764,
    "pressure": 291,
    "temperature": 23
  },
  {
    "timestamp": "2024-05-28T10:59:42.334071",
    "altitude": 613,
    "pressure": 372,
    "temperature": 31
  },
  {
    "timestamp": "2024-05-28T10:59:43.369426",
    "altitude": 492,
    "pressure": 2,
    "temperature": 9
  },
  {
    "timestamp": "2024-05-28T10:59:44.403154",
    "altitude": 545,
    "pressure": 9,
    "temperature": 9
  },
  {
    "timestamp": "2024-05-28T10:59:45.419856",
    "altitude": 80,
    "pressure": 162,
    "temperature": 32
  },
  {
    "timestamp": "2024-05-28T10:59:46.451406",
    "altitude": 123,
    "pressure": 160,
    "temperature": 29
  },
  {
    "timestamp": "2024-05-28T10:59:47.492731",
    "altitude": 375,
    "pressure": 93,
    "temperature": 1
  },
  {
    "timestamp": "2024-05-28T10:59:48.543552",
    "altitude": 402,
    "pressure": 7,
    "temperature": 5
  },
  {
    "timestamp": "2024-05-28T10:59:49.592293",
    "altitude": 9,
    "pressure": 81,
    "temperature": 35
  },
  {
    "timestamp": "2024-05-28T10:59:50.635142",
    "altitude": 627,
    "pressure": 119,
    "temperature": 9
  },
  {
    "timestamp": "2024-05-28T10:59:51.679547",
    "altitude": 780,
    "pressure": 326,
    "temperature": 12
  },
  {
    "timestamp": "2024-05-28T10:59:52.721245",
    "altitude": 119,
    "pressure": 316,
    "temperature": 9
  },
  {
    "timestamp": "2024-05-28T10:59:53.766130",
    "altitude": 399,
    "pressure": 379,
    "temperature": 33
  },
  {
    "timestamp": "2024-05-28T10:59:54.813583",
    "altitude": 844,
    "pressure": 386,
    "temperature": 27
  },
  {
    "timestamp": "2024-05-28T10:59:55.860052",
    "altitude": 835,
    "pressure": 255,
    "temperature": 33
  },
  {
    "timestamp": "2024-05-28T10:59:56.899970",
    "altitude": 905,
    "pressure": 338,
    "temperature": 29
  },
  {
    "timestamp": "2024-05-28T10:59:57.944168",
    "altitude": 665,
    "pressure": 345,
    "temperature": 12
  },
  {
    "timestamp": "2024-05-28T10:59:58.978369",
    "altitude": 126,
    "pressure": 337,
    "temperature": 27
  },
  {
    "timestamp": "2024-05-28T11:00:00.071515",
    "altitude": 563,
    "pressure": 13,
    "temperature": 24
  },
  {
    "timestamp": "2024-05-28T11:00:01.381621",
    "altitude": 223,
    "pressure": 319,
    "temperature": 25
  },
  {
    "timestamp": "2024-05-28T11:00:02.504973",
    "altitude": 399,
    "pressure": 331,
    "temperature": 1
  },
  {
    "timestamp": "2024-05-28T11:00:03.536288",
    "altitude": 623,
    "pressure": 404,
    "temperature": 17
  },
  {
    "timestamp": "2024-05-28T11:00:04.570937",
    "altitude": 752,
    "pressure": 426,
    "temperature": 26
  },
  {
    "timestamp": "2024-05-28T11:00:05.609766",
    "altitude": 625,
    "pressure": 102,
    "temperature": 35
  },
  {
    "timestamp": "2024-05-28T11:00:06.644604",
    "altitude": 786,
    "pressure": 295,
    "temperature": 14
  },
  {
    "timestamp": "2024-05-28T11:00:07.692656",
    "altitude": 783,
    "pressure": 241,
    "temperature": 33
  },
  {
    "timestamp": "2024-05-28T11:00:08.742403",
    "altitude": 733,
    "pressure": 51,
    "temperature": 10
  },
  {
    "timestamp": "2024-05-28T11:00:09.797787",
    "altitude": 478,
    "pressure": 211,
    "temperature": 36
  },
  {
    "timestamp": "2024-05-28T11:00:10.863695",
    "altitude": 292,
    "pressure": 438,
    "temperature": 38
  },
  {
    "timestamp": "2024-05-28T11:00:11.912223",
    "altitude": 331,
    "pressure": 307,
    "temperature": 13
  },
  {
    "timestamp": "2024-05-28T11:00:12.959656",
    "altitude": 491,
    "pressure": 334,
    "temperature": 37
  },
  {
    "timestamp": "2024-05-28T11:00:14.004940",
    "altitude": 125,
    "pressure": 15,
    "temperature": 39
  },
  {
    "timestamp": "2024-05-28T11:00:15.045073",
    "altitude": 654,
    "pressure": 226,
    "temperature": 20
  },
  {
    "timestamp": "2024-05-28T11:00:16.100926",
    "altitude": 676,
    "pressure": 352,
    "temperature": 35
  },
  {
    "timestamp": "2024-05-28T11:00:17.147008",
    "altitude": 836,
    "pressure": 347,
    "temperature": 19
  },
  {
    "timestamp": "2024-05-28T11:00:18.325325",
    "altitude": 445,
    "pressure": 414,
    "temperature": 13
  },
  {
    "timestamp": "2024-05-28T11:00:19.480153",
    "altitude": 582,
    "pressure": 281,
    "temperature": 13
  },
  {
    "timestamp": "2024-05-28T11:00:20.529650",
    "altitude": 0,
    "pressure": 151,
    "temperature": 36
  },
  {
    "timestamp": "2024-05-28T11:00:21.583796",
    "altitude": 19,
    "pressure": 208,
    "temperature": 21
  },
  {
    "timestamp": "2024-05-28T11:00:22.634301",
    "altitude": 571,
    "pressure": 257,
    "temperature": 13
  },
  {
    "timestamp": "2024-05-28T11:00:23.681655",
    "altitude": 801,
    "pressure": 379,
    "temperature": 14
  },
  {
    "timestamp": "2024-05-28T11:00:24.733266",
    "altitude": 951,
    "pressure": 164,
    "temperature": 25
  },
  {
    "timestamp": "2024-05-28T11:00:25.785237",
    "altitude": 99,
    "pressure": 283,
    "temperature": 9
  },
  {
    "timestamp": "2024-05-28T11:00:29.616037",
    "altitude": 601,
    "pressure": 230,
    "temperature": 37
  },
  {
    "timestamp": "2024-05-28T11:00:30.654562",
    "altitude": 318,
    "pressure": 72,
    "temperature": 0
  },
  {
    "timestamp": "2024-05-28T11:00:31.696123",
    "altitude": 550,
    "pressure": 49,
    "temperature": 25
  },
  {
    "timestamp": "2024-05-28T11:00:32.737664",
    "altitude": 433,
    "pressure": 396,
    "temperature": 19
  },
  {
    "timestamp": "2024-05-28T11:00:33.787750",
    "altitude": 7,
    "pressure": 171,
    "temperature": 19
  },
  {
    "timestamp": "2024-05-28T11:00:34.843046",
    "altitude": 754,
    "pressure": 277,
    "temperature": 2
  },
  {
    "timestamp": "2024-05-28T11:00:35.888715",
    "altitude": 302,
    "pressure": 250,
    "temperature": 19
  },
  {
    "timestamp": "2024-05-28T11:00:36.932262",
    "altitude": 906,
    "pressure": 161,
    "temperature": 16
  },
  {
    "timestamp": "2024-05-28T11:00:37.978878",
    "altitude": 785,
    "pressure": 347,
    "temperature": 25
  },
  {
    "timestamp": "2024-05-28T11:00:39.042516",
    "altitude": 166,
    "pressure": 337,
    "temperature": 19
  },
  {
    "timestamp": "2024-05-28T11:00:40.111332",
    "altitude": 436,
    "pressure": 445,
    "temperature": 30
  },
  {
    "timestamp": "2024-05-28T11:00:41.163377",
    "altitude": 385,
    "pressure": 395,
    "temperature": 10
  },
  {
    "timestamp": "2024-05-28T11:00:42.210185",
    "altitude": 929,
    "pressure": 356,
    "temperature": 17
  },
  {
    "timestamp": "2024-05-28T11:00:43.258362",
    "altitude": 341,
    "pressure": 205,
    "temperature": 6
  },
  {
    "timestamp": "2024-05-28T11:00:44.293806",
    "altitude": 189,
    "pressure": 410,
    "temperature": 5
  },
  {
    "timestamp": "2024-05-28T11:00:46.310813",
    "altitude": 693,
    "pressure": 200,
    "temperature": 4
  },
  {
    "timestamp": "2024-05-28T11:00:47.338199",
    "altitude": 313,
    "pressure": 486,
    "temperature": 13
  },
  {
    "timestamp": "2024-05-28T11:00:48.376384",
    "altitude": 184,
    "pressure": 358,
    "temperature": 36
  },
  {
    "timestamp": "2024-05-28T11:00:49.404929",
    "altitude": 868,
    "pressure": 20,
    "temperature": 10
  },
  {
    "timestamp": "2024-05-28T11:00:50.438484",
    "altitude": 893,
    "pressure": 209,
    "temperature": 1
  },
  {
    "timestamp": "2024-05-28T11:00:51.478075",
    "altitude": 83,
    "pressure": 30,
    "temperature": 30
  },
  {
    "timestamp": "2024-05-28T11:00:52.525805",
    "altitude": 308,
    "pressure": 329,
    "temperature": 34
  },
  {
    "timestamp": "2024-05-28T11:00:53.565532",
    "altitude": 113,
    "pressure": 8,
    "temperature": 10
  },
  {
    "timestamp": "2024-05-28T11:00:54.608104",
    "altitude": 988,
    "pressure": 160,
    "temperature": 3
  },
  {
    "timestamp": "2024-05-28T11:00:55.638587",
    "altitude": 418,
    "pressure": 190,
    "temperature": 35
  },
  {
    "timestamp": "2024-05-28T11:00:56.678843",
    "altitude": 738,
    "pressure": 180,
    "temperature": 26
  },
  {
    "timestamp": "2024-05-28T11:00:57.727619",
    "altitude": 52,
    "pressure": 133,
    "temperature": 21
  },
  {
    "timestamp": "2024-05-28T11:00:58.770102",
    "altitude": 986,
    "pressure": 415,
    "temperature": 36
  },
  {
    "timestamp": "2024-05-28T11:00:59.813348",
    "altitude": 677,
    "pressure": 303,
    "temperature": 12
  },
  {
    "timestamp": "2024-05-28T11:02:06.568247",
    "altitude": 867,
    "pressure": 339,
    "temperature": 20
  },
  {
    "timestamp": "2024-05-28T11:02:07.619170",
    "altitude": 34,
    "pressure": 148,
    "temperature": 19
  },
  {
    "timestamp": "2024-05-28T11:02:08.674216",
    "altitude": 131,
    "pressure": 281,
    "temperature": 0
  },
  {
    "timestamp": "2024-05-28T11:02:09.715740",
    "altitude": 123,
    "pressure": 247,
    "temperature": 18
  },
  {
    "timestamp": "2024-05-28T11:02:10.789853",
    "altitude": 144,
    "pressure": 97,
    "temperature": 30
  },
  {
    "timestamp": "2024-05-28T11:02:11.835712",
    "altitude": 12,
    "pressure": 401,
    "temperature": 30
  },
  {
    "timestamp": "2024-05-28T11:02:12.888742",
    "altitude": 897,
    "pressure": 377,
    "temperature": 26
  },
  {
    "timestamp": "2024-05-28T11:02:13.942486",
    "altitude": 403,
    "pressure": 224,
    "temperature": 11
  },
  {
    "timestamp": "2024-05-28T11:02:16.580746",
    "altitude": 539,
    "pressure": 17,
    "temperature": 15
  },
  {
    "timestamp": "2024-05-28T11:02:17.633673",
    "altitude": 273,
    "pressure": 206,
    "temperature": 7
  },
  {
    "timestamp": "2024-05-28T11:03:51.568214",
    "altitude": 259,
    "pressure": 393,
    "temperature": 15
  },
  {
    "timestamp": "2024-05-28T11:03:52.630419",
    "altitude": 974,
    "pressure": 237,
    "temperature": 17
  },
  {
    "timestamp": "2024-05-28T11:03:53.668958",
    "altitude": 465,
    "pressure": 466,
    "temperature": 28
  },
  {
    "timestamp": "2024-05-28T11:03:54.711255",
    "altitude": 131,
    "pressure": 292,
    "temperature": 11
  },
  {
    "timestamp": "2024-05-28T11:03:55.735577",
    "altitude": 450,
    "pressure": 379,
    "temperature": 12
  },
  {
    "timestamp": "2024-05-28T11:03:56.786302",
    "altitude": 3,
    "pressure": 293,
    "temperature": 5
  },
  {
    "timestamp": "2024-05-28T11:04:53.722089",
    "altitude": 785,
    "pressure": 20,
    "temperature": 6
  },
  {
    "timestamp": "2024-05-28T11:04:54.811505",
    "altitude": 160,
    "pressure": 195,
    "temperature": 13
  },
  {
    "timestamp": "2024-05-28T11:04:55.870517",
    "altitude": 764,
    "pressure": 305,
    "temperature": 33
  },
  {
    "timestamp": "2024-05-28T11:04:56.915876",
    "altitude": 870,
    "pressure": 92,
    "temperature": 21
  },
  {
    "timestamp": "2024-05-28T11:04:57.959466",
    "altitude": 796,
    "pressure": 412,
    "temperature": 32
  },
  {
    "timestamp": "2024-05-28T11:04:58.995252",
    "altitude": 271,
    "pressure": 213,
    "temperature": 10
  },
  {
    "timestamp": "2024-05-28T11:05:00.042997",
    "altitude": 827,
    "pressure": 11,
    "temperature": 38
  },
  {
    "timestamp": "2024-05-28T11:05:02.576425",
    "altitude": 152,
    "pressure": 460,
    "temperature": 9
  },
  {
    "timestamp": "2024-05-28T11:05:03.624289",
    "altitude": 994,
    "pressure": 418,
    "temperature": 37
  },
  {
    "timestamp": "2024-05-28T11:05:04.678921",
    "altitude": 357,
    "pressure": 132,
    "temperature": 2
  },
  {
    "timestamp": "2024-05-28T11:05:05.736477",
    "altitude": 433,
    "pressure": 450,
    "temperature": 17
  },
  {
    "timestamp": "2024-05-28T11:05:06.793426",
    "altitude": 329,
    "pressure": 313,
    "temperature": 27
  },
  {
    "timestamp": "2024-05-28T11:05:07.837659",
    "altitude": 215,
    "pressure": 96,
    "temperature": 2
  },
  {
    "timestamp": "2024-05-28T11:05:08.892897",
    "altitude": 171,
    "pressure": 401,
    "temperature": 22
  },
  {
    "timestamp": "2024-05-28T11:05:09.942582",
    "altitude": 30,
    "pressure": 42,
    "temperature": 34
  },
  {
    "timestamp": "2024-05-28T11:05:10.992648",
    "altitude": 874,
    "pressure": 81,
    "temperature": 12
  },
  {
    "timestamp": "2024-05-28T11:05:12.049469",
    "altitude": 688,
    "pressure": 383,
    "temperature": 22
  },
  {
    "timestamp": "2024-05-28T11:05:13.104212",
    "altitude": 960,
    "pressure": 69,
    "temperature": 35
  },
  {
    "timestamp": "2024-05-28T11:05:14.160849",
    "altitude": 46,
    "pressure": 129,
    "temperature": 27
  },
  {
    "timestamp": "2024-05-28T11:05:30.572937",
    "altitude": 949,
    "pressure": 395,
    "temperature": 26
  },
  {
    "timestamp": "2024-05-28T11:05:31.620777",
    "altitude": 130,
    "pressure": 106,
    "temperature": 15
  },
  {
    "timestamp": "2024-05-28T11:05:32.668369",
    "altitude": 301,
    "pressure": 269,
    "temperature": 17
  },
  {
    "timestamp": "2024-05-28T11:05:35.571581",
    "altitude": 505,
    "pressure": 454,
    "temperature": 9
  },
  {
    "timestamp": "2024-05-28T11:05:36.614108",
    "altitude": 258,
    "pressure": 241,
    "temperature": 1
  },
  {
    "timestamp": "2024-05-28T11:05:37.656992",
    "altitude": 646,
    "pressure": 32,
    "temperature": 11
  },
  {
    "timestamp": "2024-05-28T11:05:38.718642",
    "altitude": 983,
    "pressure": 273,
    "temperature": 9
  },
  {
    "timestamp": "2024-05-28T11:06:31.573928",
    "altitude": 924,
    "pressure": 422,
    "temperature": 8
  },
  {
    "timestamp": "2024-05-28T13:16:17.314520",
    "altitude": 456,
    "pressure": 345,
    "temperature": 22
  },
  {
    "timestamp": "2024-05-28T13:16:18.406556",
    "altitude": 323,
    "pressure": 352,
    "temperature": 9
  },
  {
    "timestamp": "2024-05-28T13:16:19.453149",
    "altitude": 352,
    "pressure": 289,
    "temperature": 29
  },
  {
    "timestamp": "2024-05-28T13:16:20.489272",
    "altitude": 143,
    "pressure": 79,
    "temperature": 12
  },
  {
    "timestamp": "2024-05-28T13:16:21.517596",
    "altitude": 54,
    "pressure": 336,
    "temperature": 16
  },
  {
    "timestamp": "2024-05-28T13:16:22.677481",
    "altitude": 436,
    "pressure": 381,
    "temperature": 32
  },
  {
    "timestamp": "2024-05-28T13:16:23.846156",
    "altitude": 779,
    "pressure": 396,
    "temperature": 3
  },
  {
    "timestamp": "2024-05-28T13:16:25.009683",
    "altitude": 117,
    "pressure": 84,
    "temperature": 7
  },
  {
    "timestamp": "2024-05-28T13:16:26.056922",
    "altitude": 598,
    "pressure": 376,
    "temperature": 32
  },
  {
    "timestamp": "2024-05-28T13:16:27.111694",
    "altitude": 989,
    "pressure": 87,
    "temperature": 5
  },
  {
    "timestamp": "2024-05-28T13:16:28.156557",
    "altitude": 247,
    "pressure": 226,
    "temperature": 2
  },
  {
    "timestamp": "2024-05-28T13:16:29.193359",
    "altitude": 136,
    "pressure": 245,
    "temperature": 10
  },
  {
    "timestamp": "2024-05-28T13:16:30.238469",
    "altitude": 597,
    "pressure": 310,
    "temperature": 23
  },
  {
    "timestamp": "2024-05-28T13:16:31.543851",
    "altitude": 274,
    "pressure": 89,
    "temperature": 7
  },
  {
    "timestamp": "2024-05-28T13:16:32.694265",
    "altitude": 909,
    "pressure": 306,
    "temperature": 5
  },
  {
    "timestamp": "2024-05-28T13:16:33.750136",
    "altitude": 960,
    "pressure": 89,
    "temperature": 39
  },
  {
    "timestamp": "2024-05-28T13:16:34.849174",
    "altitude": 258,
    "pressure": 415,
    "temperature": 6
  },
  {
    "timestamp": "2024-05-28T13:16:35.996713",
    "altitude": 283,
    "pressure": 17,
    "temperature": 18
  },
  {
    "timestamp": "2024-05-28T13:16:37.915137",
    "altitude": 50,
    "pressure": 273,
    "temperature": 11
  },
  {
    "timestamp": "2024-05-28T13:16:38.997532",
    "altitude": 39,
    "pressure": 211,
    "temperature": 24
  },
  {
    "timestamp": "2024-05-28T13:16:40.020596",
    "altitude": 247,
    "pressure": 240,
    "temperature": 4
  },
  {
    "timestamp": "2024-05-28T13:16:41.056553",
    "altitude": 898,
    "pressure": 379,
    "temperature": 3
  },
  {
    "timestamp": "2024-05-28T13:16:42.081242",
    "altitude": 522,
    "pressure": 264,
    "temperature": 15
  },
  {
    "timestamp": "2024-05-28T13:16:43.113775",
    "altitude": 464,
    "pressure": 296,
    "temperature": 27
  },
  {
    "timestamp": "2024-05-28T13:16:44.148639",
    "altitude": 786,
    "pressure": 75,
    "temperature": 12
  },
  {
    "timestamp": "2024-05-28T13:16:45.177868",
    "altitude": 571,
    "pressure": 475,
    "temperature": 8
  },
  {
    "timestamp": "2024-05-28T13:16:46.214998",
    "altitude": 518,
    "pressure": 470,
    "temperature": 38
  },
  {
    "timestamp": "2024-05-28T13:16:47.253770",
    "altitude": 105,
    "pressure": 32,
    "temperature": 13
  },
  {
    "timestamp": "2024-05-28T13:16:48.297989",
    "altitude": 254,
    "pressure": 325,
    "temperature": 5
  },
  {
    "timestamp": "2024-05-28T13:16:49.365685",
    "altitude": 997,
    "pressure": 79,
    "temperature": 15
  },
  {
    "timestamp": "2024-05-28T13:16:50.555516",
    "altitude": 857,
    "pressure": 190,
    "temperature": 26
  },
  {
    "timestamp": "2024-05-28T13:16:51.657210",
    "altitude": 468,
    "pressure": 428,
    "temperature": 6
  },
  {
    "timestamp": "2024-05-28T13:16:52.711411",
    "altitude": 787,
    "pressure": 314,
    "temperature": 10
  },
  {
    "timestamp": "2024-05-28T13:16:53.759199",
    "altitude": 211,
    "pressure": 420,
    "temperature": 35
  },
  {
    "timestamp": "2024-05-28T13:16:54.791182",
    "altitude": 674,
    "pressure": 477,
    "temperature": 9
  },
  {
    "timestamp": "2024-05-28T13:16:55.848501",
    "altitude": 276,
    "pressure": 34,
    "temperature": 16
  },
  {
    "timestamp": "2024-05-28T13:16:56.892010",
    "altitude": 764,
    "pressure": 291,
    "temperature": 23
  },
  {
    "timestamp": "2024-05-28T13:16:57.949897",
    "altitude": 613,
    "pressure": 372,
    "temperature": 31
  },
  {
    "timestamp": "2024-05-28T13:16:59.012954",
    "altitude": 492,
    "pressure": 2,
    "temperature": 9
  },
  {
    "timestamp": "2024-05-28T13:17:00.050046",
    "altitude": 545,
    "pressure": 9,
    "temperature": 9
  },
  {
    "timestamp": "2024-05-28T13:17:01.100332",
    "altitude": 123,
    "pressure": 160,
    "temperature": 29
  },
  {
    "timestamp": "2024-05-28T13:17:02.165654",
    "altitude": 402,
    "pressure": 7,
    "temperature": 5
  },
  {
    "timestamp": "2024-05-28T13:17:03.229209",
    "altitude": 627,
    "pressure": 119,
    "temperature": 9
  },
  {
    "timestamp": "2024-05-28T13:17:04.272441",
    "altitude": 119,
    "pressure": 316,
    "temperature": 9
  },
  {
    "timestamp": "2024-05-28T13:17:05.305899",
    "altitude": 844,
    "pressure": 386,
    "temperature": 27
  },
  {
    "timestamp": "2024-05-28T13:17:06.346266",
    "altitude": 835,
    "pressure": 255,
    "temperature": 33
  },
  {
    "timestamp": "2024-05-28T13:17:26.258011",
    "altitude": 836,
    "pressure": 347,
    "temperature": 19
  },
  {
    "timestamp": "2024-05-28T13:17:27.373431",
    "altitude": 445,
    "pressure": 414,
    "temperature": 13
  },
  {
    "timestamp": "2024-05-28T13:17:28.435545",
    "altitude": 582,
    "pressure": 281,
    "temperature": 13
  },
  {
    "timestamp": "2024-05-28T13:17:29.485290",
    "altitude": 0,
    "pressure": 151,
    "temperature": 36
  },
  {
    "timestamp": "2024-05-28T13:17:30.532722",
    "altitude": 19,
    "pressure": 208,
    "temperature": 21
  },
  {
    "timestamp": "2024-05-28T13:17:31.843881",
    "altitude": 571,
    "pressure": 257,
    "temperature": 13
  }
]